bluesky/resources/navdata/TACAN_freq.dat
bluesky/resources/navdata/__init__.py
bluesky/resources/navdata/airports.dat
bluesky/resources/navdata/apt.zip
bluesky/resources/navdata/awy.dat
bluesky/resources/navdata/coastlines.dat
bluesky/resources/navdata/fix.dat
bluesky/resources/navdata/geo_declination_data.csv
bluesky/resources/navdata/icao-countries-new.dat
bluesky/resources/navdata/icao-countries.dat
bluesky/resources/navdata/nav.dat
bluesky/resources/navdata/waypoints-old.dat
bluesky/resources/navdata/fir/EBBU.txt
bluesky/resources/navdata/fir/EDGG.txt
bluesky/resources/navdata/fir/EDMM.txt
bluesky/resources/navdata/fir/EDWW.txt
bluesky/resources/navdata/fir/EFES.txt
bluesky/resources/navdata/fir/EFPS.txt
bluesky/resources/navdata/fir/EGGX.txt
bluesky/resources/navdata/fir/EGPX.txt
bluesky/resources/navdata/fir/EGTT.txt
bluesky/resources/navdata/fir/EHAA.txt
bluesky/resources/navdata/fir/EIDW.txt
bluesky/resources/navdata/fir/EISN.txt
bluesky/resources/navdata/fir/EKDK.txt
bluesky/resources/navdata/fir/ENBD.txt
bluesky/resources/navdata/fir/ENOS.txt
bluesky/resources/navdata/fir/ENSV.txt
bluesky/resources/navdata/fir/ENTR.txt
bluesky/resources/navdata/fir/ESMM.txt
bluesky/resources/navdata/fir/ESOS.txt
bluesky/resources/navdata/fir/LBSR.txt
bluesky/resources/navdata/fir/LCCC.txt
bluesky/resources/navdata/fir/LECB.txt
bluesky/resources/navdata/fir/LECM.txt
bluesky/resources/navdata/fir/LFBB.txt
bluesky/resources/navdata/fir/LFEE.txt
bluesky/resources/navdata/fir/LFFF.txt
bluesky/resources/navdata/fir/LFMM.txt
bluesky/resources/navdata/fir/LFRR.txt
bluesky/resources/navdata/fir/LIBB.txt
bluesky/resources/navdata/fir/LIMM.txt
bluesky/resources/navdata/fir/LIRR.txt
bluesky/resources/navdata/fir/LOVV.txt
bluesky/resources/navdata/fir/LPPC.txt
bluesky/resources/navdata/fir/LRBB.txt
bluesky/resources/navdata/fir/LSAZ.txt
bluesky/resources/navdata/fir/LWSS.txt
bluesky_navdata-2024.12.18.dist-info/METADATA
bluesky_navdata-2024.12.18.dist-info/WHEEL
bluesky_navdata-2024.12.18.dist-info/RECORD
